bits/__init__.py
bits/mssql/__init__.py
bits_mssql-1.0.1.dist-info/METADATA
bits_mssql-1.0.1.dist-info/WHEEL
bits_mssql-1.0.1.dist-info/top_level.txt
bits_mssql-1.0.1.dist-info/RECORD
