Metadata-Version: 2.1
Name: bits-mssql
Version: 1.0.1
Summary: BITS MSSQL
Home-page: UNKNOWN
Author: Lukas Karlsson
Author-email: karlsson@broadinstitute.org
License: Apache Software License
Platform: UNKNOWN
Requires-Dist: pymssql (<3.0)
